KinetiKit/__init__.py
KinetiKit/settings.py
KinetiKit/units.py
KinetiKit/artists/__init__.py
KinetiKit/artists/plot3scales/__init__.py
KinetiKit/artists/plot3scales/_plot3scales.py
KinetiKit/artists/plotparams/__init__.py
KinetiKit/artists/plotparams/_plotparams.py
KinetiKit/data/__init__.py
KinetiKit/data/lib/__init__.py
KinetiKit/data/lib/_lib.py
KinetiKit/fit/__init__.py
KinetiKit/fit/lib/__init__.py
KinetiKit/fit/lib/_lib.py
KinetiKit/kit/__init__.py
KinetiKit/kit/_ald.py
KinetiKit/kit/_alignment.py
KinetiKit/kit/_displaying.py
KinetiKit/kit/_mathfuncs.py
KinetiKit/kit/_readtools.py
KinetiKit/kit/_savetools.py
KinetiKit/sim/__init__.py
KinetiKit/sim/lib/_IRFfuncs.py
KinetiKit/sim/lib/__init__.py
KinetiKit/sim/lib/_excitation.py
KinetiKit/sim/lib/_simfunc.py
KinetiKit/sim/lib/_simrate.py
KinetiKit/sim/systems/__init__.py
KinetiKit/sim/systems/_baseModels.py
KinetiKit/sim/systems/_exponential.py
KinetiKit/sim/systems/_heterostructures.py
KinetiKit/sim/systems/_heterostructuresWithTraps.py
KinetiKit/sim/systems/_mono.py
KinetiKit/sim/systems/_monoWithTraps.py
KinetiKit/sim/systems/_other.py
KinetiKit/sim/time/__init__.py
KinetiKit/sim/time/_time.py
KinetiKit/sim/vizfuncs/__init__.py
KinetiKit/sim/vizfuncs/_vizfuncs.py
KinetiKit/sim/vizfuncs/_widgettoolkit.py
KinetiKit-0.2.0.dist-info/LICENSE
KinetiKit-0.2.0.dist-info/METADATA
KinetiKit-0.2.0.dist-info/WHEEL
KinetiKit-0.2.0.dist-info/top_level.txt
KinetiKit-0.2.0.dist-info/RECORD
