Metadata-Version: 2.1
Name: KinetiKit
Version: 0.2.0
Summary: Tools for comparing and kinetically simulating time-resolved data
Home-page: UNKNOWN
Author: Natalia Spitha
Author-email: natalia.spitha@gmail.com
License: UNKNOWN
Platform: UNKNOWN
Requires-Python: >=3.6
License-File: LICENSE
Requires-Dist: matplotlib (>=3.0)
Requires-Dist: numpy (>=1.15.0)
Requires-Dist: scipy
Requires-Dist: ipywidgets
